clistyle/__init__.py
clistyle/__main__.py
clistyle/version.py
clistyle-1.0.0.dist-info/LICENSE
clistyle-1.0.0.dist-info/METADATA
clistyle-1.0.0.dist-info/WHEEL
clistyle-1.0.0.dist-info/top_level.txt
clistyle-1.0.0.dist-info/zip-safe
clistyle-1.0.0.dist-info/RECORD
